{"about.md":"BhJOBEVM","blog_android_2020_ubuntu 20.04编译android-6.0.1_r77.md":"A6t9HfIV","blog_coin_2021_about coin.md":"CY1Bpk9f","blog_computernetworks_index.md":"DEvYrImZ","blog_computernetworks_一文详解socket.md":"DRjNeu0J","blog_computernetworks_一文详解tcp.md":"BzzzqAof","blog_computernetworks_物理层、数据链路层、网络层.md":"fjzrcKJw","blog_ddd_domain-driven-design.md":"DI0TDi6-","blog_grpc_2020_grpc example.md":"C9MRvtAT","blog_java_index.md":"C8CPtuFQ","blog_java_java bufferedreader流.md":"DMGGGPgM","blog_java_java io.md":"DXlGNGSm","blog_java_java optional类.md":"D_Sgxv_C","blog_java_java stream.md":"o7w4w7OU","blog_java_java 双端队列 deque.md":"USyz-YyQ","blog_java_java 正则表达式.md":"DeU0Fv9L","blog_java_java 泛型.md":"2l0XlqFE","blog_java_java中为什么使用向上转型而不直接创建子类对象.md":"CcE7dWvm","blog_java_java中实现pojo类的序列化.md":"DtHb3jpw","blog_java_java的注解与反射机制.md":"CM5Ubx1T","blog_java_java集合框架综述.md":"se5HJLQF","blog_java_jdbc各个类的详解.md":"C5sFRUJK","blog_java_初识多线程.md":"BEhu1UQu","blog_javaweb_cookie和session、sessionid的那些事儿.md":"0Qvw3IQX","blog_javaweb_filter和listener总结.md":"DdDiJDhu","blog_javaweb_http协议.md":"ZnHp0OHp","blog_javaweb_http协议无状态中的【状态】到底指的是什么？！.md":"Bizo5gVj","blog_javaweb_index.md":"CIbBVdRi","blog_javaweb_j2ee开发开发中po_bo_vo_dto_pojo_dao的概念及其作用.md":"Bs2oLc9y","blog_javaweb_java开发的主流框架演变.md":"D7NGQrfD","blog_javaweb_json和ajax总结.md":"FVjeLU8k","blog_javaweb_jsp总结.md":"CRDIPruA","blog_javaweb_jstl和el表达式.md":"D2sjlxJv","blog_javaweb_mvc模式和三层架构.md":"FtCHev1c","blog_javaweb_request和response.md":"D37W6gwJ","blog_javaweb_servlet总结.md":"EMU909x6","blog_javaweb_tomcat深入理解.md":"D1SbPI7l","blog_javaweb_web概述.md":"D0liwsV_","blog_javaweb_xml总结.md":"CbpVFbfv","blog_javaweb_会话技术.md":"IESa4m3H","blog_jdk_2020_2020-10-最后的免费jdk下载.md":"DbAYHlIx","blog_kubernetes_k8s no space left.md":"BzcqUluM","blog_kubernetes_k8s prometheus-operator mysqld-exporter servicemonitor not work.md":"BKlQY8xT","blog_leet-code_1.两数之和.md":"C53TDINn","blog_leet-code_100.相同的树.md":"DprpS7ns","blog_leet-code_101.对称二叉树.md":"BfbFD17e","blog_leet-code_102.二叉树的层序遍历.md":"BpH3W5FJ","blog_leet-code_104.二叉树的最大深度.md":"PQy4NUfJ","blog_leet-code_1047.删除字符串中的所有相邻重复项.md":"DkeKNZnS","blog_leet-code_106.从中序和后序遍历序列构造二叉树.md":"CK6xfdxE","blog_leet-code_107.二叉树的层序遍历ⅱ.md":"DGZIbhUf","blog_leet-code_110.平衡二叉树.md":"Dt2q_fkU","blog_leet-code_111.二叉树的最小深度.md":"Bsnm3-ET","blog_leet-code_112.路径总和.md":"C-G5rQfm","blog_leet-code_113.路径总和ⅱ.md":"Ck9nJ9zV","blog_leet-code_117.填充每个节点的下一个右侧节点指针ⅱ.md":"Gm1Dlfns","blog_leet-code_142.环形链表ⅱ.md":"D4GXk3Gm","blog_leet-code_144.二叉树的前序遍历.md":"Cu68up2h","blog_leet-code_145.二叉树的后序遍历.md":"C-rwD_Ra","blog_leet-code_146.lru缓存.md":"DE-FMbNg","blog_leet-code_15.三数之和.md":"CfKfs1pg","blog_leet-code_150.逆波兰表达式求值.md":"IQKScnEv","blog_leet-code_151.反转字符串中的单词.md":"BdOsxBRM","blog_leet-code_155.最小栈.md":"BMkKIeVq","blog_leet-code_160.相交链表.md":"CmvxWxJV","blog_leet-code_18.四数之和.md":"MI87nuv3","blog_leet-code_19.删除链表的倒数第n个节点.md":"DPI7n5VG","blog_leet-code_199.二叉树的右视图.md":"agYaQBtQ","blog_leet-code_20.有效的括号.md":"C8SFrNZx","blog_leet-code_202.快乐数.md":"Cf1x2_ZQ","blog_leet-code_203.移除链表元素.md":"B5nkZ-va","blog_leet-code_206.反转链表.md":"DRy1RNCI","blog_leet-code_209.长度最小的子数组.md":"BLMS317s","blog_leet-code_222.完全二叉树的节点个数.md":"BDlKClpO","blog_leet-code_225.用队列实现栈.md":"CpmO894x","blog_leet-code_226.翻转二叉树.md":"C22z4bmc","blog_leet-code_232.用栈实现队列.md":"Cd-kbVab","blog_leet-code_236.二叉树的最近公共祖先.md":"BLoNAydA","blog_leet-code_239.滑动窗口最大值.md":"9QMEvRHH","blog_leet-code_24.两两交换链表中的节点.md":"BtT51VO1","blog_leet-code_242.有效的字母异位词.md":"NXymqW6_","blog_leet-code_257.二叉树的所有路径.md":"DfE4ceYI","blog_leet-code_26.删除有序数据中的重复项.md":"n0QtG3Ro","blog_leet-code_27.移除元素.md":"kIWG2et5","blog_leet-code_28.找出字符串中第一个匹配项的下标.md":"CfNskO5K","blog_leet-code_283.移动零.md":"D8MwEAi4","blog_leet-code_3.无重复字符的最长子串.md":"KmstGpQ2","blog_leet-code_34.在排序数组中查找元素的第一个和最后一个位置.md":"CU0KO05l","blog_leet-code_344.反转字符串.md":"CsPELRS1","blog_leet-code_347.前k个高频元素.md":"BDi3Pe2E","blog_leet-code_349.两个数组的交集.md":"CITG_Nf3","blog_leet-code_35.搜索插入位置.md":"DtX2By0m","blog_leet-code_350.两个数组的交集ⅱ.md":"BqD4Uhel","blog_leet-code_367.有效的完全平方数.md":"BnyVxSsO","blog_leet-code_383.赎金信.md":"CeofQX5h","blog_leet-code_404.左叶子之和.md":"rqcHlYOj","blog_leet-code_429.n叉树的层序遍历.md":"0v8uF-mx","blog_leet-code_438.找到字符串中所有字母异位词.md":"DEDMjwio","blog_leet-code_454.四数相加ⅱ.md":"DusID6Uz","blog_leet-code_459.重复的子字符串.md":"UJIYrU-w","blog_leet-code_49.字母异位词分组.md":"BgZZGFfA","blog_leet-code_501.二叉搜索树中的众数.md":"DmmE2ZnH","blog_leet-code_513.找树左下角的值.md":"CsyDOK1l","blog_leet-code_515.在每个树行中找最大值.md":"BIQa4k_b","blog_leet-code_530.二叉搜索树的最小绝对差.md":"CQ2tKIai","blog_leet-code_54.螺旋矩阵.md":"CaBIEGZ6","blog_leet-code_541.反转字符串ⅱ.md":"BUJZxtE9","blog_leet-code_559.n叉树的最大深度.md":"DBUehdZN","blog_leet-code_572.另一棵树的子树.md":"DriZJUe_","blog_leet-code_59.螺旋矩阵ⅱ.md":"euSWBjsB","blog_leet-code_617.合并二叉树.md":"DC8ExRSL","blog_leet-code_637.二叉树的层平均值.md":"DCzZsrdS","blog_leet-code_654.最大二叉树.md":"CgPqfmlp","blog_leet-code_69.x的平方根.md":"CG2uSGuk","blog_leet-code_700.二叉搜索树中的搜索.md":"DpbyXWP6","blog_leet-code_704.二分查找.md":"uzcT0aDl","blog_leet-code_707.设计链表.md":"B3b0KRRc","blog_leet-code_71.简化路径.md":"CvRhKlqX","blog_leet-code_76.最小覆盖子串.md":"D8O1Y9of","blog_leet-code_80.删除有序数据中的重复项ⅱ.md":"yUupIq2W","blog_leet-code_844.比较含退格的字符串.md":"DYcKvtU1","blog_leet-code_904.水果成篮.md":"B9ckLFAK","blog_leet-code_94.二叉树的中序遍历.md":"CbIC6pXT","blog_leet-code_977.有序数组的平方.md":"CAXw6Qif","blog_leet-code_98.验证二叉搜索树.md":"DJaFzpLP","blog_leet-code_index.md":"BuALw7nv","blog_leet-code_剑指offer-05.替换空格.md":"ZfZVL2Q7","blog_leet-code_剑指offer-58-ⅱ.左旋转字符串.md":"Dt2QwIEE","blog_life_index.md":"BTEO8jpQ","blog_life_做你认为正确的事.md":"Dkxm3OY2","blog_life_关于受害者有罪论.md":"BYtkaNJe","blog_life_十年前的论坛.md":"DZcTk9hi","blog_linux_index.md":"DPanYO64","blog_linux_linux常用的基本命令.md":"BGQ6ZoaJ","blog_linux_linux概述及环境搭建.md":"BkZBW0Yb","blog_linux_vim使用及账号用户管理.md":"CseTuAWL","blog_linux_三种软件安装方式及服务器基本环境搭建.md":"DEL2tLYF","blog_mysql_dml语言.md":"D9qFCHXw","blog_mysql_index.md":"BKibxawp","blog_mysql_mysql中的关联查询（内连接、外连接、自连接）.md":"Dfb9n9Qu","blog_mysql_mysql主从复制.md":"Cn6qExWg","blog_mysql_mysql函数.md":"hdyYTn_L","blog_mysql_mysql数据库设计规范.md":"CUH2So1f","blog_mysql_sql语句的执行顺序.md":"BZnPu64S","blog_mysql_一文详解数据库连接池.md":"CTxR4QEh","blog_mysql_事务和索引.md":"MnY-4kdM","blog_mysql_使用dql查询数据.md":"DoxaFFuQ","blog_mysql_初识mysql.md":"BvbFNUr0","blog_mysql_数据库中为什么不推荐使用外键约束.md":"C5VUGB9w","blog_mysql_数据库操作.md":"DaGMQPt1","blog_mysql_权限及如何设计数据库.md":"4L0jdoiU","blog_mysql_连接查询时on与where的区别.md":"B5OY4eWi","blog_openjdk_2019_openjdk-research.md":"BNCm3pA_","blog_springboot_index.md":"C3xbfE1K","blog_springboot_maven的进阶使用.md":"Bhfqjdca","blog_springboot_nginx的使用教程.md":"V7NLUpBq","blog_springboot_redis的基本使用.md":"DQr309j4","blog_springboot_springboottest详解.md":"CLRKgTkA","blog_springboot_webclient的基本使用.md":"Cr_5dHzi","blog_springboot_yaml配置注入.md":"DXe6nHuu","blog_springboot_全局统一响应格式、参数校验、异常处理.md":"CbwXgzwJ","blog_springboot_分库分表与sharding-jdbc.md":"DZiCvIfB","blog_springboot_初识springboot.md":"Ts6G-BML","blog_springboot_启动剖析之pom.xml、@springbootapplication.md":"DmCC-H6r","blog_springboot_启动剖析之springapplication.run.md":"DlzMTy_-","blog_springboot_多环境开发配置.md":"CBlNhjau","blog_springboot_定时任务框架xxl-job.md":"9BuN-I4_","blog_springboot_整合druid.md":"Bu7ya_jN","blog_springboot_整合jdbc.md":"ZYJXRgLO","blog_springboot_整合mybatis.md":"HA8AYjDa","blog_springboot_缓存注解spring-cache.md":"B_Xkd1Jx","blog_springboot_自动配置原理.md":"B_I44pdw","blog_springboot_自定义starter.md":"C_vRzFVm","blog_springboot_迈入前后端分离时代.md":"jBNifbaE","blog_springboot_集成swagger与springdoc.md":"C59RebXk","blog_tensorflow_2020_tensorflow的55个经典案例.md":"CIrmwGcd","en_index.md":"B2GdBWHT","index.md":"t6WP6bTu","readme.md":"DqYDWb5f","sponsor.md":"c99O-J2S","stock_202411_量化交易小白交易日志-20241118.md":"BEvhd33s","stock_202412_量化交易小白交易日志-20241218.md":"CUkgnbcP","stock_202501_量化交易小白交易日志-20250101.md":"D_9eVOpD","stock_202501_量化小白交易日志-20250106.md":"DesagZpC","stock_202502_量化交易小白交易日志-20250201.md":"DPUvq_g4","stock_index.md":"MBjzZPs5","timeline.md":"tOCWxS-C"}
